wqio/__init__.py
wqio/bootstrap.py
wqio/datacollections.py
wqio/datasets.py
wqio/features.py
wqio/hydro.py
wqio/ros.py
wqio/samples.py
wqio/theil.py
wqio/validate.py
wqio/viz.py
wqio/tests/__init__.py
wqio/tests/conftest.py
wqio/tests/helpers.py
wqio/tests/test_bootstrap.py
wqio/tests/test_datacollections.py
wqio/tests/test_datasets.py
wqio/tests/test_features.py
wqio/tests/test_features_plotting.py
wqio/tests/test_hydro.py
wqio/tests/test_ros.py
wqio/tests/test_samples.py
wqio/tests/test_theil.py
wqio/tests/test_validate.py
wqio/tests/test_viz.py
wqio/tests/_baseline_images/__init__.py
wqio/tests/_baseline_images/features_tests/__init__.py
wqio/tests/_baseline_images/features_tests/test_ds__plot_NDs_both.png
wqio/tests/_baseline_images/features_tests/test_ds__plot_NDs_effluent.png
wqio/tests/_baseline_images/features_tests/test_ds__plot_NDs_influent.png
wqio/tests/_baseline_images/features_tests/test_ds__plot_NDs_neither.png
wqio/tests/_baseline_images/features_tests/test_ds_boxplot_bacteria_geomean.png
wqio/tests/_baseline_images/features_tests/test_ds_boxplot_custom_offset.png
wqio/tests/_baseline_images/features_tests/test_ds_boxplot_custom_position.png
wqio/tests/_baseline_images/features_tests/test_ds_boxplot_default.png
wqio/tests/_baseline_images/features_tests/test_ds_boxplot_linscale.png
wqio/tests/_baseline_images/features_tests/test_ds_boxplot_no_mean.png
wqio/tests/_baseline_images/features_tests/test_ds_boxplot_no_notch.png
wqio/tests/_baseline_images/features_tests/test_ds_boxplot_patch_artists.png
wqio/tests/_baseline_images/features_tests/test_ds_boxplot_provided_ax.png
wqio/tests/_baseline_images/features_tests/test_ds_boxplot_single_tick.png
wqio/tests/_baseline_images/features_tests/test_ds_boxplot_single_tick_no_name.png
wqio/tests/_baseline_images/features_tests/test_ds_boxplot_width.png
wqio/tests/_baseline_images/features_tests/test_ds_boxplot_with_ylabel.png
wqio/tests/_baseline_images/features_tests/test_ds_probplot.png
wqio-0.7.2.dist-info/LICENSE
wqio-0.7.2.dist-info/METADATA
wqio-0.7.2.dist-info/WHEEL
wqio-0.7.2.dist-info/top_level.txt
wqio-0.7.2.dist-info/RECORD
