Metadata-Version: 2.2
Name: wqio
Version: 0.7.2
Summary: wqio: Water Quality Inflow/Outflow
Home-page: https://github.com/International-BMP-Database/wqio
Download-URL: https://github.com/International-BMP-Database/wqio/archive/main.zip
Author: Paul Hobson (Herrera Environmental Consultants)
Author-email: phobson@herrerainc.com
License: BSD 3-clause
Platform: Python 3.10 and later.
Classifier: License :: OSI Approved :: BSD License
Classifier: Operating System :: OS Independent
Classifier: Programming Language :: Python
Classifier: Intended Audience :: Science/Research
Classifier: Topic :: Software Development :: Libraries :: Python Modules
Classifier: Programming Language :: Python :: 3.9
Classifier: Programming Language :: Python :: 3.10
Classifier: Programming Language :: Python :: 3.11
Classifier: Programming Language :: Python :: 3.12
License-File: LICENSE
Requires-Dist: numpy
Requires-Dist: scipy
Requires-Dist: matplotlib
Requires-Dist: pandas
Requires-Dist: statsmodels
Requires-Dist: seaborn
Requires-Dist: probscale
Dynamic: author
Dynamic: author-email
Dynamic: classifier
Dynamic: description
Dynamic: download-url
Dynamic: home-page
Dynamic: license
Dynamic: platform
Dynamic: requires-dist
Dynamic: summary
